{"created_at":"Fri Jun 25 11:27:51 +0000 2021","id":1408386452514164736,"id_str":"1408386452514164736","text":"RT @garuda_gia: Garuda Aerospace UGV'S Against COVID-19\n.\nFounder: @AgnishwarJ \n#ugvcl #CoronavirusIndia https:\/\/t.co\/LFYOEEaHAs","source":"\u003ca href=\"https:\/\/mobile.twitter.com\" rel=\"nofollow\"\u003eTwitter Web App\u003c\/a\u003e","truncated":false,"in_reply_to_status_id":null,"in_reply_to_status_id_str":null,"in_reply_to_user_id":null,"in_reply_to_user_id_str":null,"in_reply_to_screen_name":null,"user":{"id":1391770801880272896,"id_str":"1391770801880272896","name":"Abinaya","screen_name":"Abinaya80968152","location":null,"url":null,"description":null,"translator_type":"none","protected":false,"verified":false,"followers_count":0,"friends_count":3,"listed_count":0,"favourites_count":82,"statuses_count":104,"created_at":"Mon May 10 15:03:30 +0000 2021","utc_offset":null,"time_zone":null,"geo_enabled":false,"lang":null,"contributors_enabled":false,"is_translator":false,"profile_background_color":"F5F8FA","profile_background_image_url":"","profile_background_image_url_https":"","profile_background_tile":false,"profile_link_color":"1DA1F2","profile_sidebar_border_color":"C0DEED","profile_sidebar_fill_color":"DDEEF6","profile_text_color":"333333","profile_use_background_image":true,"profile_image_url":"http:\/\/abs.twimg.com\/sticky\/default_profile_images\/default_profile_normal.png","profile_image_url_https":"https:\/\/abs.twimg.com\/sticky\/default_profile_images\/default_profile_normal.png","default_profile":true,"default_profile_image":false,"following":null,"follow_request_sent":null,"notifications":null,"withheld_in_countries":[]},"geo":null,"coordinates":null,"place":null,"contributors":null,"retweeted_status":{"created_at":"Mon Jun 07 11:30:00 +0000 2021","id":1401864013974097926,"id_str":"1401864013974097926","text":"Garuda Aerospace UGV'S Against COVID-19\n.\nFounder: @AgnishwarJ \n#ugvcl #CoronavirusIndia https:\/\/t.co\/LFYOEEaHAs","display_text_range":[0,88],"source":"\u003ca href=\"https:\/\/mobile.twitter.com\" rel=\"nofollow\"\u003eTwitter Web App\u003c\/a\u003e","truncated":false,"in_reply_to_status_id":null,"in_reply_to_status_id_str":null,"in_reply_to_user_id":null,"in_reply_to_user_id_str":null,"in_reply_to_screen_name":null,"user":{"id":925594812127920128,"id_str":"925594812127920128","name":"Garuda Aerospace","screen_name":"garuda_gia","location":"Chennai, India - Global","url":"http:\/\/www.garudaaerospace.com\/","description":"Garuda Aerospace focuses on the design, building and customization of unmanned aerial vehicles (UAVs) or drones for various applications.","translator_type":"none","protected":false,"verified":false,"followers_count":307,"friends_count":67,"listed_count":3,"favourites_count":562,"statuses_count":851,"created_at":"Wed Nov 01 05:26:14 +0000 2017","utc_offset":null,"time_zone":null,"geo_enabled":true,"lang":null,"contributors_enabled":false,"is_translator":false,"profile_background_color":"000000","profile_background_image_url":"http:\/\/abs.twimg.com\/images\/themes\/theme1\/bg.png","profile_background_image_url_https":"https:\/\/abs.twimg.com\/images\/themes\/theme1\/bg.png","profile_background_tile":false,"profile_link_color":"1B95E0","profile_sidebar_border_color":"000000","profile_sidebar_fill_color":"000000","profile_text_color":"000000","profile_use_background_image":false,"profile_image_url":"http:\/\/pbs.twimg.com\/profile_images\/1062278203098640385\/Vp0SV86g_normal.jpg","profile_image_url_https":"https:\/\/pbs.twimg.com\/profile_images\/1062278203098640385\/Vp0SV86g_normal.jpg","profile_banner_url":"https:\/\/pbs.twimg.com\/profile_banners\/925594812127920128\/1621864019","default_profile":false,"default_profile_image":false,"following":null,"follow_request_sent":null,"notifications":null,"withheld_in_countries":[]},"geo":null,"coordinates":null,"place":null,"contributors":null,"is_quote_status":false,"quote_count":0,"reply_count":10,"retweet_count":20,"favorite_count":32,"entities":{"hashtags":[{"text":"ugvcl","indices":[64,70]},{"text":"CoronavirusIndia","indices":[71,88]}],"urls":[],"user_mentions":[{"screen_name":"AgnishwarJ","name":"AgnishwarJayaprakash","id":3188447983,"id_str":"3188447983","indices":[51,62]}],"symbols":[],"media":[{"id":1401851387642744832,"id_str":"1401851387642744832","indices":[89,112],"additional_media_info":{"monetizable":false},"media_url":"http:\/\/pbs.twimg.com\/ext_tw_video_thumb\/1401851387642744832\/pu\/img\/8OjuDx_sS8x14M2Q.jpg","media_url_https":"https:\/\/pbs.twimg.com\/ext_tw_video_thumb\/1401851387642744832\/pu\/img\/8OjuDx_sS8x14M2Q.jpg","url":"https:\/\/t.co\/LFYOEEaHAs","display_url":"pic.twitter.com\/LFYOEEaHAs","expanded_url":"https:\/\/twitter.com\/garuda_gia\/status\/1401864013974097926\/video\/1","type":"photo","sizes":{"thumb":{"w":150,"h":150,"resize":"crop"},"medium":{"w":640,"h":1138,"resize":"fit"},"large":{"w":640,"h":1138,"resize":"fit"},"small":{"w":382,"h":680,"resize":"fit"}}}]},"extended_entities":{"media":[{"id":1401851387642744832,"id_str":"1401851387642744832","indices":[89,112],"additional_media_info":{"monetizable":false},"media_url":"http:\/\/pbs.twimg.com\/ext_tw_video_thumb\/1401851387642744832\/pu\/img\/8OjuDx_sS8x14M2Q.jpg","media_url_https":"https:\/\/pbs.twimg.com\/ext_tw_video_thumb\/1401851387642744832\/pu\/img\/8OjuDx_sS8x14M2Q.jpg","url":"https:\/\/t.co\/LFYOEEaHAs","display_url":"pic.twitter.com\/LFYOEEaHAs","expanded_url":"https:\/\/twitter.com\/garuda_gia\/status\/1401864013974097926\/video\/1","type":"video","video_info":{"aspect_ratio":[320,569],"duration_millis":11900,"variants":[{"bitrate":2176000,"content_type":"video\/mp4","url":"https:\/\/video.twimg.com\/ext_tw_video\/1401851387642744832\/pu\/vid\/640x1138\/4Iy9QEv6RUJNRypQ.mp4?tag=12"},{"bitrate":632000,"content_type":"video\/mp4","url":"https:\/\/video.twimg.com\/ext_tw_video\/1401851387642744832\/pu\/vid\/320x568\/4itZJnHEvG-YxlTk.mp4?tag=12"},{"bitrate":950000,"content_type":"video\/mp4","url":"https:\/\/video.twimg.com\/ext_tw_video\/1401851387642744832\/pu\/vid\/480x852\/1u1LOJPWJI4lX57-.mp4?tag=12"},{"content_type":"application\/x-mpegURL","url":"https:\/\/video.twimg.com\/ext_tw_video\/1401851387642744832\/pu\/pl\/2QymX-r8NgCSaRdO.m3u8?tag=12&container=fmp4"}]},"sizes":{"thumb":{"w":150,"h":150,"resize":"crop"},"medium":{"w":640,"h":1138,"resize":"fit"},"large":{"w":640,"h":1138,"resize":"fit"},"small":{"w":382,"h":680,"resize":"fit"}}}]},"favorited":false,"retweeted":false,"possibly_sensitive":false,"filter_level":"low","lang":"en"},"is_quote_status":false,"quote_count":0,"reply_count":0,"retweet_count":0,"favorite_count":0,"entities":{"hashtags":[{"text":"ugvcl","indices":[80,86]},{"text":"CoronavirusIndia","indices":[87,104]}],"urls":[],"user_mentions":[{"screen_name":"garuda_gia","name":"Garuda Aerospace","id":925594812127920128,"id_str":"925594812127920128","indices":[3,14]},{"screen_name":"AgnishwarJ","name":"AgnishwarJayaprakash","id":3188447983,"id_str":"3188447983","indices":[67,78]}],"symbols":[],"media":[{"id":1401851387642744832,"id_str":"1401851387642744832","indices":[105,128],"additional_media_info":{"monetizable":false},"media_url":"http:\/\/pbs.twimg.com\/ext_tw_video_thumb\/1401851387642744832\/pu\/img\/8OjuDx_sS8x14M2Q.jpg","media_url_https":"https:\/\/pbs.twimg.com\/ext_tw_video_thumb\/1401851387642744832\/pu\/img\/8OjuDx_sS8x14M2Q.jpg","url":"https:\/\/t.co\/LFYOEEaHAs","display_url":"pic.twitter.com\/LFYOEEaHAs","expanded_url":"https:\/\/twitter.com\/garuda_gia\/status\/1401864013974097926\/video\/1","type":"photo","sizes":{"thumb":{"w":150,"h":150,"resize":"crop"},"medium":{"w":640,"h":1138,"resize":"fit"},"large":{"w":640,"h":1138,"resize":"fit"},"small":{"w":382,"h":680,"resize":"fit"}},"source_status_id":1401864013974097926,"source_status_id_str":"1401864013974097926","source_user_id":925594812127920128,"source_user_id_str":"925594812127920128"}]},"extended_entities":{"media":[{"id":1401851387642744832,"id_str":"1401851387642744832","indices":[105,128],"additional_media_info":{"monetizable":false},"media_url":"http:\/\/pbs.twimg.com\/ext_tw_video_thumb\/1401851387642744832\/pu\/img\/8OjuDx_sS8x14M2Q.jpg","media_url_https":"https:\/\/pbs.twimg.com\/ext_tw_video_thumb\/1401851387642744832\/pu\/img\/8OjuDx_sS8x14M2Q.jpg","url":"https:\/\/t.co\/LFYOEEaHAs","display_url":"pic.twitter.com\/LFYOEEaHAs","expanded_url":"https:\/\/twitter.com\/garuda_gia\/status\/1401864013974097926\/video\/1","type":"video","video_info":{"aspect_ratio":[320,569],"duration_millis":11900,"variants":[{"bitrate":2176000,"content_type":"video\/mp4","url":"https:\/\/video.twimg.com\/ext_tw_video\/1401851387642744832\/pu\/vid\/640x1138\/4Iy9QEv6RUJNRypQ.mp4?tag=12"},{"bitrate":632000,"content_type":"video\/mp4","url":"https:\/\/video.twimg.com\/ext_tw_video\/1401851387642744832\/pu\/vid\/320x568\/4itZJnHEvG-YxlTk.mp4?tag=12"},{"bitrate":950000,"content_type":"video\/mp4","url":"https:\/\/video.twimg.com\/ext_tw_video\/1401851387642744832\/pu\/vid\/480x852\/1u1LOJPWJI4lX57-.mp4?tag=12"},{"content_type":"application\/x-mpegURL","url":"https:\/\/video.twimg.com\/ext_tw_video\/1401851387642744832\/pu\/pl\/2QymX-r8NgCSaRdO.m3u8?tag=12&container=fmp4"}]},"sizes":{"thumb":{"w":150,"h":150,"resize":"crop"},"medium":{"w":640,"h":1138,"resize":"fit"},"large":{"w":640,"h":1138,"resize":"fit"},"small":{"w":382,"h":680,"resize":"fit"}},"source_status_id":1401864013974097926,"source_status_id_str":"1401864013974097926","source_user_id":925594812127920128,"source_user_id_str":"925594812127920128"}]},"favorited":false,"retweeted":false,"possibly_sensitive":false,"filter_level":"low","lang":"en","timestamp_ms":"1624620471491"}